water_prop/__init__.py
water_prop/water_data.csv
water_prop-1.1.1.dist-info/licenses/LICENSE
water_prop-1.1.1.dist-info/METADATA
water_prop-1.1.1.dist-info/WHEEL
water_prop-1.1.1.dist-info/top_level.txt
water_prop-1.1.1.dist-info/RECORD
