Metadata-Version: 2.4
Name: water_prop
Version: 1.1.1
Summary: Provides vapor pressure and specific gravity of water by temperature
Author: Nilesh Mishra
License: MIT
Classifier: Programming Language :: Python :: 3
Classifier: License :: OSI Approved :: MIT License
Classifier: Operating System :: OS Independent
Requires-Python: >=3.6
License-File: LICENSE
Dynamic: license-file
